source_pipedrive/__init__.py
source_pipedrive/extractor.py
source_pipedrive/manifest.yaml
source_pipedrive/run.py
source_pipedrive/schemas/activities.json
source_pipedrive/schemas/activity_fields.json
source_pipedrive/schemas/activity_types.json
source_pipedrive/schemas/currencies.json
source_pipedrive/schemas/deal_fields.json
source_pipedrive/schemas/deal_products.json
source_pipedrive/schemas/deals.json
source_pipedrive/schemas/files.json
source_pipedrive/schemas/filters.json
source_pipedrive/schemas/goals.json
source_pipedrive/schemas/lead_labels.json
source_pipedrive/schemas/leads.json
source_pipedrive/schemas/mail.json
source_pipedrive/schemas/notes.json
source_pipedrive/schemas/organization_fields.json
source_pipedrive/schemas/organizations.json
source_pipedrive/schemas/permission_sets.json
source_pipedrive/schemas/person_fields.json
source_pipedrive/schemas/persons.json
source_pipedrive/schemas/pipelines.json
source_pipedrive/schemas/product_fields.json
source_pipedrive/schemas/products.json
source_pipedrive/schemas/roles.json
source_pipedrive/schemas/stages.json
source_pipedrive/schemas/users.json
source_pipedrive/source.py
airbyte_source_pipedrive-2.3.6.dist-info/METADATA
airbyte_source_pipedrive-2.3.6.dist-info/WHEEL
airbyte_source_pipedrive-2.3.6.dist-info/entry_points.txt
airbyte_source_pipedrive-2.3.6.dist-info/RECORD
